yeet_api/__init__.py
yeet_api/_configs.py
yeet_api/device.py
yeet_api/exceptions.py
yeet_api-0.2.0.dist-info/entry_points.txt
yeet_api-0.2.0.dist-info/LICENSE
yeet_api-0.2.0.dist-info/METADATA
yeet_api-0.2.0.dist-info/WHEEL
yeet_api-0.2.0.dist-info/RECORD
