Metadata-Version: 2.1
Name: yeet-api
Version: 0.2.0
Summary: Core API for yeet tools
License: MIT
Author: YeetCode Developers
Author-email: YeetCode-devs@protonmail.com
Requires-Python: >=3.10,<4.0
Classifier: License :: OSI Approved :: MIT License
Classifier: Programming Language :: Python :: 3
Classifier: Programming Language :: Python :: 3.10
Classifier: Programming Language :: Python :: 3.11
Requires-Dist: gitpython (>=3.1.31,<4.0.0)
